{
  "buttonToModeActionsMap": {
    "0": [
      {
        "longPress": false,
        "modeUuid": "80e4ea4c-82a8-477e-89de-fd2fb37f4e8f",
        "toggle": false
      }
    ],
    "1": [
      {
        "longPress": false,
        "modeUuid": "e305d7e5-5dcb-4efb-aa32-afaa574bc503",
        "toggle": false
      }
    ],
    "2": [
      {
        "longPress": false,
        "modeUuid": "bdcdac57-9f20-4e59-ad7b-47f7bc65f92a",
        "toggle": false
      }
    ],
    "3": [
      {
        "longPress": false,
        "modeUuid": "ca236e7e-a577-4159-9b4d-14be96a0e21a",
        "toggle": false
      }
    ],
    "4": [
      {
        "longPress": false,
        "modeUuid": "f569525f-14ed-4ed5-930a-539c069b7e3f",
        "toggle": true
      }
    ],
    "6": [
      {
        "longPress": false,
        "modeUuid": "6488968d-4833-46ab-b924-3cf5aa90d636",
        "toggle": true
      }
    ],
    "7": [
      {
        "longPress": false,
        "modeUuid": "fa3734e0-7a3d-4f23-b53a-020ca21857c3",
        "toggle": true
      }
    ],
    "8": [
      {
        "longPress": false,
        "modeUuid": "daf53639-9518-48db-bd63-19cde7bf9a96",
        "toggle": true
      }
    ],
    "9": [
      {
        "longPress": false,
        "modeUuid": "e4948829-9655-4fc1-8a3a-0ad466ece749",
        "toggle": false
      }
    ],
    "10": [
      {
        "longPress": false,
        "modeUuid": "242f7006-11a9-4303-8858-d9e2d065c3c8",
        "toggle": false
      }
    ]
  },
  "keyRepeatInterval": 30,
  "modes": [
    {
      "uuid": "067e6162-3b6f-4ae2-a171-2470b63dff00",
      "axisToActionsMap": {
        "0": [
          {
            "type": "de.bwravencl.controllerbuddy.input.action.AxisToAxisAction",
            "data": {
              "deadZone": 0.0,
              "exponent": 1.0,
              "initialValue": 0.0,
              "maxValue": 1.0,
              "minValue": -1.0,
              "virtualAxis": "RZ",
              "invert": false,
              "description": "Plane control: yaw"
            }
          }
        ],
        "1": [
          {
            "type": "de.bwravencl.controllerbuddy.input.action.AxisToRelativeAxisAction",
            "data": {
              "hapticFeedback": true,
              "maxRelativeSpeed": 4.0,
              "deadZone": 0.25,
              "exponent": 2.0,
              "initialValue": 1.0,
              "maxValue": 1.0,
              "minValue": -1.0,
              "virtualAxis": "Z",
              "invert": false,
              "description": "Engines throttle control"
            }
          }
        ],
        "2": [
          {
            "type": "de.bwravencl.controllerbuddy.input.action.AxisToAxisAction",
            "data": {
              "deadZone": 0.0,
              "exponent": 1.0,
              "initialValue": 0.0,
              "maxValue": 1.0,
              "minValue": -1.0,
              "virtualAxis": "X",
              "invert": false,
              "description": "Plane control: roll"
            }
          }
        ],
        "3": [
          {
            "type": "de.bwravencl.controllerbuddy.input.action.AxisToAxisAction",
            "data": {
              "deadZone": 0.0,
              "exponent": 1.0,
              "initialValue": 0.0,
              "maxValue": 1.0,
              "minValue": -1.0,
              "virtualAxis": "Y",
              "invert": false,
              "description": "Plane control: pitch"
            }
          }
        ],
        "4": [
          {
            "type": "de.bwravencl.controllerbuddy.input.action.AxisToButtonAction",
            "data": {
              "longPress": false,
              "maxAxisValue": 1.0,
              "minAxisValue": 0.5,
              "buttonId": 1,
              "maxActivationInterval": 0,
              "minActivationInterval": 50,
              "description": "Fire weapon group 2"
            }
          },
          {
            "type": "de.bwravencl.controllerbuddy.input.action.AxisToButtonAction",
            "data": {
              "longPress": false,
              "maxAxisValue": 1.0,
              "minAxisValue": 0.5,
              "buttonId": 7,
              "maxActivationInterval": 0,
              "minActivationInterval": 50,
              "description": "Fire weapon group 3 / Engine blip switch (ignition interruption)"
            }
          }
        ],
        "5": [
          {
            "type": "de.bwravencl.controllerbuddy.input.action.AxisToButtonAction",
            "data": {
              "longPress": false,
              "maxAxisValue": 1.0,
              "minAxisValue": 0.5,
              "buttonId": 0,
              "maxActivationInterval": 0,
              "minActivationInterval": 50,
              "description": "Fire weapon group 1"
            }
          }
        ]
      },
      "buttonToActionsMap": {
        "2": [
          {
            "type": "de.bwravencl.controllerbuddy.input.action.ButtonToAxisResetAction",
            "data": {
              "activation": "SINGLE_IMMEDIATELY",
              "fluid": false,
              "longPress": false,
              "resetValue": 0.0,
              "virtualAxis": "RX",
              "description": "Reset camera"
            }
          },
          {
            "type": "de.bwravencl.controllerbuddy.input.action.ButtonToAxisResetAction",
            "data": {
              "activation": "SINGLE_IMMEDIATELY",
              "fluid": false,
              "longPress": false,
              "resetValue": 0.0,
              "virtualAxis": "RY",
              "description": "Reset camera"
            }
          },
          {
            "type": "de.bwravencl.controllerbuddy.input.action.ButtonToKeyAction",
            "data": {
              "activation": "REPEAT",
              "keystroke": {
                "keyCodes": [
                  "Num5"
                ],
                "modifierCodes": []
              },
              "longPress": false,
              "maxActivationInterval": 0,
              "minActivationInterval": 50,
              "description": "Reset camera"
            }
          },
          {
            "type": "de.bwravencl.controllerbuddy.input.action.NullAction",
            "data": {}
          },
          {
            "type": "de.bwravencl.controllerbuddy.input.action.ButtonToKeyAction",
            "data": {
              "activation": "REPEAT",
              "keystroke": {
                "keyCodes": [
                  "Num*"
                ],
                "modifierCodes": []
              },
              "longPress": false,
              "maxActivationInterval": 0,
              "minActivationInterval": 50,
              "description": "Pilot head: reset zoom"
            }
          }
        ],
        "11": [
          {
            "type": "de.bwravencl.controllerbuddy.input.action.ButtonToButtonAction",
            "data": {
              "longPress": false,
              "buttonId": 9,
              "maxActivationInterval": 0,
              "minActivationInterval": 50,
              "description": "AI-autopilot for level flight: on/off"
            }
          }
        ],
        "12": [
          {
            "type": "de.bwravencl.controllerbuddy.input.action.ButtonToKeyAction",
            "data": {
              "activation": "REPEAT",
              "keystroke": {
                "keyCodes": [
                  "G"
                ],
                "modifierCodes": []
              },
              "longPress": false,
              "maxActivationInterval": 0,
              "minActivationInterval": 50,
              "description": "Gear up/down"
            }
          }
        ],
        "13": [
          {
            "type": "de.bwravencl.controllerbuddy.input.action.ButtonToButtonAction",
            "data": {
              "longPress": false,
              "buttonId": 14,
              "maxActivationInterval": 0,
              "minActivationInterval": 50,
              "description": "Flaps up"
            }
          }
        ],
        "14": [
          {
            "type": "de.bwravencl.controllerbuddy.input.action.ButtonToKeyAction",
            "data": {
              "activation": "REPEAT",
              "keystroke": {
                "keyCodes": [
                  "F"
                ],
                "modifierCodes": []
              },
              "longPress": false,
              "maxActivationInterval": 0,
              "minActivationInterval": 50,
              "description": "Flaps down"
            }
          }
        ]
      }
    },
    {
      "uuid": "daf53639-9518-48db-bd63-19cde7bf9a96",
      "axisToActionsMap": {},
      "buttonToActionsMap": {
        "0": [
          {
            "type": "de.bwravencl.controllerbuddy.input.action.ButtonToPressOnScreenKeyboardKeyAction",
            "data": {
              "lockKey": false,
              "longPress": false
            }
          }
        ],
        "1": [
          {
            "type": "de.bwravencl.controllerbuddy.input.action.ButtonToPressOnScreenKeyboardKeyAction",
            "data": {
              "lockKey": true,
              "longPress": false
            }
          }
        ],
        "3": [
          {
            "type": "de.bwravencl.controllerbuddy.input.action.ButtonToReleaseAllOnScreenKeyboardKeysAction",
            "data": {
              "longPress": false
            }
          }
        ],
        "11": [
          {
            "type": "de.bwravencl.controllerbuddy.input.action.ButtonToSelectOnScreenKeyboardKeyAction",
            "data": {
              "direction": "UP",
              "longPress": false
            }
          }
        ],
        "12": [
          {
            "type": "de.bwravencl.controllerbuddy.input.action.ButtonToSelectOnScreenKeyboardKeyAction",
            "data": {
              "direction": "DOWN",
              "longPress": false
            }
          }
        ],
        "13": [
          {
            "type": "de.bwravencl.controllerbuddy.input.action.ButtonToSelectOnScreenKeyboardKeyAction",
            "data": {
              "direction": "LEFT",
              "longPress": false
            }
          }
        ],
        "14": [
          {
            "type": "de.bwravencl.controllerbuddy.input.action.ButtonToSelectOnScreenKeyboardKeyAction",
            "data": {
              "direction": "RIGHT",
              "longPress": false
            }
          }
        ]
      }
    },
    {
      "uuid": "6488968d-4833-46ab-b924-3cf5aa90d636",
      "axisToActionsMap": {
        "4": [
          {
            "type": "de.bwravencl.controllerbuddy.input.action.AxisToKeyAction",
            "data": {
              "maxAxisValue": 1.0,
              "minAxisValue": 0.5,
              "activation": "REPEAT",
              "keystroke": {
                "keyCodes": [
                  "B"
                ],
                "modifierCodes": []
              },
              "longPress": false,
              "maxActivationInterval": 0,
              "minActivationInterval": 50,
              "description": "Drop bombs, containers, paratroopers, emit smoke"
            }
          }
        ],
        "5": [
          {
            "type": "de.bwravencl.controllerbuddy.input.action.AxisToKeyAction",
            "data": {
              "maxAxisValue": 1.0,
              "minAxisValue": 0.5,
              "activation": "REPEAT",
              "keystroke": {
                "keyCodes": [
                  "R"
                ],
                "modifierCodes": []
              },
              "longPress": false,
              "maxActivationInterval": 0,
              "minActivationInterval": 50,
              "description": "Launch rockets / Jet boosters"
            }
          }
        ]
      },
      "buttonToActionsMap": {
        "4": [
          {
            "type": "de.bwravencl.controllerbuddy.input.action.ButtonToKeyAction",
            "data": {
              "activation": "REPEAT",
              "keystroke": {
                "keyCodes": [
                  "V"
                ],
                "modifierCodes": []
              },
              "longPress": false,
              "maxActivationInterval": 0,
              "minActivationInterval": 50,
              "description": "Bomb sight"
            }
          }
        ],
        "11": [
          {
            "type": "de.bwravencl.controllerbuddy.input.action.ButtonToButtonAction",
            "data": {
              "longPress": false,
              "buttonId": 5,
              "maxActivationInterval": 0,
              "minActivationInterval": 50,
              "description": "AirBrakes on/off"
            }
          }
        ],
        "12": [
          {
            "type": "de.bwravencl.controllerbuddy.input.action.ButtonToKeyAction",
            "data": {
              "activation": "REPEAT",
              "keystroke": {
                "keyCodes": [
                  "N"
                ],
                "modifierCodes": []
              },
              "longPress": false,
              "maxActivationInterval": 0,
              "minActivationInterval": 50,
              "description": "Bomb bay doors toggle"
            }
          }
        ],
        "13": [
          {
            "type": "de.bwravencl.controllerbuddy.input.action.ButtonToButtonAction",
            "data": {
              "longPress": false,
              "buttonId": 8,
              "maxActivationInterval": 0,
              "minActivationInterval": 50,
              "description": "Reload all guns"
            }
          }
        ]
      },
      "description": "Attack"
    },
    {
      "uuid": "f569525f-14ed-4ed5-930a-539c069b7e3f",
      "axisToActionsMap": {
        "4": [
          {
            "type": "de.bwravencl.controllerbuddy.input.action.AxisToKeyAction",
            "data": {
              "maxAxisValue": 1.0,
              "minAxisValue": 0.5,
              "activation": "REPEAT",
              "keystroke": {
                "keyCodes": [
                  ","
                ],
                "modifierCodes": []
              },
              "longPress": false,
              "maxActivationInterval": 0,
              "minActivationInterval": 50,
              "description": "Left wheel brakes"
            }
          }
        ],
        "5": [
          {
            "type": "de.bwravencl.controllerbuddy.input.action.AxisToKeyAction",
            "data": {
              "maxAxisValue": 1.0,
              "minAxisValue": 0.5,
              "activation": "REPEAT",
              "keystroke": {
                "keyCodes": [
                  "."
                ],
                "modifierCodes": []
              },
              "longPress": false,
              "maxActivationInterval": 0,
              "minActivationInterval": 50,
              "description": "Right wheel brakes"
            }
          }
        ]
      },
      "buttonToActionsMap": {
        "0": [
          {
            "type": "de.bwravencl.controllerbuddy.input.action.ButtonToButtonAction",
            "data": {
              "longPress": false,
              "buttonId": 4,
              "maxActivationInterval": 0,
              "minActivationInterval": 50,
              "description": "Tail wheel lock/unlock"
            }
          }
        ],
        "1": [
          {
            "type": "de.bwravencl.controllerbuddy.input.action.ButtonToKeyAction",
            "data": {
              "activation": "REPEAT",
              "keystroke": {
                "keyCodes": [
                  "/"
                ],
                "modifierCodes": []
              },
              "longPress": false,
              "maxActivationInterval": 0,
              "minActivationInterval": 50,
              "description": "Wheel brakes"
            }
          }
        ],
        "3": [
          {
            "type": "de.bwravencl.controllerbuddy.input.action.ButtonToButtonAction",
            "data": {
              "longPress": false,
              "buttonId": 15,
              "maxActivationInterval": 0,
              "minActivationInterval": 50,
              "description": "Canopy open/close"
            }
          }
        ],
        "6": [
          {
            "type": "de.bwravencl.controllerbuddy.input.action.ButtonToButtonAction",
            "data": {
              "longPress": false,
              "buttonId": 16,
              "maxActivationInterval": 0,
              "minActivationInterval": 50,
              "description": "Wheels parking brakes on/off"
            }
          }
        ],
        "11": [
          {
            "type": "de.bwravencl.controllerbuddy.input.action.ButtonToKeyAction",
            "data": {
              "activation": "REPEAT",
              "keystroke": {
                "keyCodes": [
                  "E"
                ],
                "modifierCodes": []
              },
              "longPress": false,
              "maxActivationInterval": 0,
              "minActivationInterval": 50,
              "description": "Engage engines start procedure / Stop engine"
            }
          }
        ]
      },
      "description": "Ground"
    },
    {
      "uuid": "242f7006-11a9-4303-8858-d9e2d065c3c8",
      "axisToActionsMap": {
        "0": [
          {
            "type": "de.bwravencl.controllerbuddy.input.action.AxisToRelativeAxisAction",
            "data": {
              "hapticFeedback": false,
              "maxRelativeSpeed": 1.0,
              "deadZone": 0.12,
              "exponent": 3.0,
              "initialValue": 0.0,
              "maxValue": 1.0,
              "minValue": -1.0,
              "virtualAxis": "RX",
              "invert": false,
              "description": "Rotate camera left/right"
            }
          }
        ],
        "1": [
          {
            "type": "de.bwravencl.controllerbuddy.input.action.AxisToRelativeAxisAction",
            "data": {
              "hapticFeedback": false,
              "maxRelativeSpeed": 1.0,
              "deadZone": 0.12,
              "exponent": 3.0,
              "initialValue": 0.0,
              "maxValue": 1.0,
              "minValue": -1.0,
              "virtualAxis": "RY",
              "invert": false,
              "description": "Rotate camera up/down"
            }
          }
        ]
      },
      "buttonToActionsMap": {
        "0": [
          {
            "type": "de.bwravencl.controllerbuddy.input.action.ButtonToKeyAction",
            "data": {
              "activation": "REPEAT",
              "keystroke": {
                "keyCodes": [
                  "Home"
                ],
                "modifierCodes": []
              },
              "longPress": false,
              "maxActivationInterval": 0,
              "minActivationInterval": 50,
              "description": "Move pilot head backward"
            }
          }
        ],
        "3": [
          {
            "type": "de.bwravencl.controllerbuddy.input.action.ButtonToKeyAction",
            "data": {
              "activation": "REPEAT",
              "keystroke": {
                "keyCodes": [
                  "Ins"
                ],
                "modifierCodes": []
              },
              "longPress": false,
              "maxActivationInterval": 0,
              "minActivationInterval": 50,
              "description": "Move pilot head forward"
            }
          }
        ],
        "7": [
          {
            "type": "de.bwravencl.controllerbuddy.input.action.ButtonToKeyAction",
            "data": {
              "activation": "REPEAT",
              "keystroke": {
                "keyCodes": [
                  "Num-"
                ],
                "modifierCodes": []
              },
              "longPress": false,
              "maxActivationInterval": 0,
              "minActivationInterval": 0,
              "description": "Pilot head: zoom out"
            }
          }
        ],
        "8": [
          {
            "type": "de.bwravencl.controllerbuddy.input.action.ButtonToKeyAction",
            "data": {
              "activation": "REPEAT",
              "keystroke": {
                "keyCodes": [
                  "Num+"
                ],
                "modifierCodes": []
              },
              "longPress": false,
              "maxActivationInterval": 0,
              "minActivationInterval": 0,
              "description": "Pilot head: zoom in"
            }
          }
        ],
        "11": [
          {
            "type": "de.bwravencl.controllerbuddy.input.action.ButtonToKeyAction",
            "data": {
              "activation": "REPEAT",
              "keystroke": {
                "keyCodes": [
                  "PgUp"
                ],
                "modifierCodes": []
              },
              "longPress": false,
              "maxActivationInterval": 0,
              "minActivationInterval": 50,
              "description": "Move pilot head up"
            }
          }
        ],
        "12": [
          {
            "type": "de.bwravencl.controllerbuddy.input.action.ButtonToKeyAction",
            "data": {
              "activation": "REPEAT",
              "keystroke": {
                "keyCodes": [
                  "PgDn"
                ],
                "modifierCodes": []
              },
              "longPress": false,
              "maxActivationInterval": 0,
              "minActivationInterval": 50,
              "description": "Move pilot head down"
            }
          }
        ],
        "13": [
          {
            "type": "de.bwravencl.controllerbuddy.input.action.ButtonToKeyAction",
            "data": {
              "activation": "REPEAT",
              "keystroke": {
                "keyCodes": [
                  "Del"
                ],
                "modifierCodes": []
              },
              "longPress": false,
              "maxActivationInterval": 0,
              "minActivationInterval": 50,
              "description": "Move pilot head left"
            }
          }
        ],
        "14": [
          {
            "type": "de.bwravencl.controllerbuddy.input.action.ButtonToKeyAction",
            "data": {
              "activation": "REPEAT",
              "keystroke": {
                "keyCodes": [
                  "End"
                ],
                "modifierCodes": []
              },
              "longPress": false,
              "maxActivationInterval": 0,
              "minActivationInterval": 50,
              "description": "Move pilot head right"
            }
          }
        ]
      },
      "description": "Look"
    },
    {
      "uuid": "e305d7e5-5dcb-4efb-aa32-afaa574bc503",
      "axisToActionsMap": {
        "1": [
          {
            "type": "de.bwravencl.controllerbuddy.input.action.AxisToRelativeAxisAction",
            "data": {
              "hapticFeedback": true,
              "maxRelativeSpeed": 4.0,
              "deadZone": 0.25,
              "exponent": 2.0,
              "initialValue": -1.0,
              "maxValue": 1.0,
              "minValue": -1.0,
              "virtualAxis": "S1",
              "invert": false,
              "description": "Engines mixture control"
            }
          }
        ]
      },
      "buttonToActionsMap": {
        "4": [
          {
            "type": "de.bwravencl.controllerbuddy.input.action.ButtonToButtonAction",
            "data": {
              "longPress": false,
              "buttonId": 18,
              "maxActivationInterval": 0,
              "minActivationInterval": 50,
              "description": "Engine superchargers mode switch"
            }
          }
        ],
        "11": [
          {
            "type": "de.bwravencl.controllerbuddy.input.action.ButtonToButtonAction",
            "data": {
              "longPress": false,
              "buttonId": 19,
              "maxActivationInterval": 0,
              "minActivationInterval": 50,
              "description": "Engines outlet cowl shutters control (A-20, Fw 190 A-5 and A-8, La-5, Ju 88, P-40, P-47, C-47)"
            }
          }
        ],
        "12": [
          {
            "type": "de.bwravencl.controllerbuddy.input.action.ButtonToButtonAction",
            "data": {
              "longPress": false,
              "buttonId": 20,
              "maxActivationInterval": 0,
              "minActivationInterval": 50,
              "description": "Engines outlet cowl shutters control (A-20, Fw 190 A-5 and A-8, La-5, Ju 88, P-40, P-47, C-47)"
            }
          }
        ],
        "13": [
          {
            "type": "de.bwravencl.controllerbuddy.input.action.ButtonToButtonAction",
            "data": {
              "longPress": false,
              "buttonId": 21,
              "maxActivationInterval": 0,
              "minActivationInterval": 50,
              "description": "Engines inlet cowl shutters control (I-16, La-5, Ju 52), Engines upper cowl flaps (A-20), Engines intercooler shutter (P-47)"
            }
          }
        ],
        "14": [
          {
            "type": "de.bwravencl.controllerbuddy.input.action.ButtonToButtonAction",
            "data": {
              "longPress": false,
              "buttonId": 22,
              "maxActivationInterval": 0,
              "minActivationInterval": 50,
              "description": "Engines inlet cowl shutters control (I-16, La-5, Ju 52), Engines upper cowl flaps (A-20), Engines intercooler shutter (P-47)"
            }
          }
        ]
      },
      "description": "Mixture / Engine"
    },
    {
      "uuid": "fa3734e0-7a3d-4f23-b53a-020ca21857c3",
      "axisToActionsMap": {
        "0": [
          {
            "type": "de.bwravencl.controllerbuddy.input.action.AxisToCursorAction",
            "data": {
              "deadZone": 0.12,
              "exponent": 2.5,
              "cursorSensitivity": 1500,
              "axis": "X",
              "invert": false
            }
          }
        ],
        "1": [
          {
            "type": "de.bwravencl.controllerbuddy.input.action.AxisToCursorAction",
            "data": {
              "deadZone": 0.12,
              "exponent": 2.5,
              "cursorSensitivity": 1500,
              "axis": "Y",
              "invert": false
            }
          }
        ],
        "4": [
          {
            "type": "de.bwravencl.controllerbuddy.input.action.AxisToMouseButtonAction",
            "data": {
              "maxAxisValue": 1.0,
              "minAxisValue": 0.5,
              "activation": "REPEAT",
              "longPress": false,
              "mouseButton": 1,
              "maxActivationInterval": 0,
              "minActivationInterval": 0
            }
          }
        ],
        "5": [
          {
            "type": "de.bwravencl.controllerbuddy.input.action.AxisToMouseButtonAction",
            "data": {
              "maxAxisValue": 1.0,
              "minAxisValue": 0.5,
              "activation": "REPEAT",
              "longPress": false,
              "mouseButton": 2,
              "maxActivationInterval": 0,
              "minActivationInterval": 0
            }
          }
        ]
      },
      "buttonToActionsMap": {
        "6": [
          {
            "type": "de.bwravencl.controllerbuddy.input.action.ButtonToMouseButtonAction",
            "data": {
              "activation": "REPEAT",
              "longPress": false,
              "mouseButton": 3,
              "maxActivationInterval": 0,
              "minActivationInterval": 0
            }
          }
        ],
        "11": [
          {
            "type": "de.bwravencl.controllerbuddy.input.action.ButtonToScrollAction",
            "data": {
              "longPress": false,
              "clicks": 10,
              "invert": false
            }
          }
        ],
        "12": [
          {
            "type": "de.bwravencl.controllerbuddy.input.action.ButtonToScrollAction",
            "data": {
              "longPress": false,
              "clicks": 10,
              "invert": true
            }
          }
        ]
      },
      "description": "Mouse"
    },
    {
      "uuid": "ca236e7e-a577-4159-9b4d-14be96a0e21a",
      "axisToActionsMap": {
        "1": [
          {
            "type": "de.bwravencl.controllerbuddy.input.action.AxisToRelativeAxisAction",
            "data": {
              "hapticFeedback": true,
              "maxRelativeSpeed": 4.0,
              "deadZone": 0.25,
              "exponent": 2.0,
              "initialValue": -1.0,
              "maxValue": 1.0,
              "minValue": -1.0,
              "virtualAxis": "S0",
              "invert": false,
              "description": "Propeller RPM control"
            }
          }
        ]
      },
      "buttonToActionsMap": {
        "4": [
          {
            "type": "de.bwravencl.controllerbuddy.input.action.ButtonToButtonAction",
            "data": {
              "longPress": false,
              "buttonId": 17,
              "maxActivationInterval": 0,
              "minActivationInterval": 50,
              "description": "Switch engines boost: on/off"
            }
          }
        ],
        "11": [
          {
            "type": "de.bwravencl.controllerbuddy.input.action.ButtonToButtonAction",
            "data": {
              "longPress": false,
              "buttonId": 23,
              "maxActivationInterval": 0,
              "minActivationInterval": 50,
              "description": "Propeller RPM control / Propellers: low pitch"
            }
          }
        ],
        "12": [
          {
            "type": "de.bwravencl.controllerbuddy.input.action.ButtonToButtonAction",
            "data": {
              "longPress": false,
              "buttonId": 24,
              "maxActivationInterval": 0,
              "minActivationInterval": 50,
              "description": "Propeller RPM control / Propellers: high pitch"
            }
          }
        ],
        "13": [
          {
            "type": "de.bwravencl.controllerbuddy.input.action.ButtonToButtonAction",
            "data": {
              "longPress": false,
              "buttonId": 2,
              "maxActivationInterval": 0,
              "minActivationInterval": 50,
              "description": "Switch propellers pitch control mode: manual/auto"
            }
          }
        ]
      },
      "description": "Prop / Engine"
    },
    {
      "uuid": "e4948829-9655-4fc1-8a3a-0ad466ece749",
      "axisToActionsMap": {},
      "buttonToActionsMap": {
        "0": [
          {
            "type": "de.bwravencl.controllerbuddy.input.action.ButtonToButtonAction",
            "data": {
              "longPress": false,
              "buttonId": 31,
              "maxActivationInterval": 0,
              "minActivationInterval": 50,
              "description": "Reset trimmers"
            }
          }
        ],
        "1": [
          {
            "type": "de.bwravencl.controllerbuddy.input.action.ButtonToButtonAction",
            "data": {
              "longPress": false,
              "buttonId": 30,
              "maxActivationInterval": 0,
              "minActivationInterval": 50,
              "description": "Rudder trim axis / Rudder trim switch: left"
            }
          }
        ],
        "2": [
          {
            "type": "de.bwravencl.controllerbuddy.input.action.ButtonToButtonAction",
            "data": {
              "longPress": false,
              "buttonId": 29,
              "maxActivationInterval": 0,
              "minActivationInterval": 50,
              "description": "Rudder trim axis / Rudder trim switch: right"
            }
          }
        ],
        "11": [
          {
            "type": "de.bwravencl.controllerbuddy.input.action.ButtonToButtonAction",
            "data": {
              "longPress": false,
              "buttonId": 25,
              "maxActivationInterval": 0,
              "minActivationInterval": 50,
              "description": "Adjustable stabilizer axis / Elevator trim switch: down / Adjustable stabilizer switch: pitch down"
            }
          }
        ],
        "12": [
          {
            "type": "de.bwravencl.controllerbuddy.input.action.ButtonToButtonAction",
            "data": {
              "longPress": false,
              "buttonId": 26,
              "maxActivationInterval": 0,
              "minActivationInterval": 50,
              "description": "Adjustable stabilizer axis / Elevator trim switch: up / Adjustable stabilizer switch: pitch up"
            }
          }
        ],
        "13": [
          {
            "type": "de.bwravencl.controllerbuddy.input.action.ButtonToButtonAction",
            "data": {
              "longPress": false,
              "buttonId": 27,
              "maxActivationInterval": 0,
              "minActivationInterval": 50,
              "description": "Aileron trim axis / Aileron trim switch: left"
            }
          }
        ],
        "14": [
          {
            "type": "de.bwravencl.controllerbuddy.input.action.ButtonToButtonAction",
            "data": {
              "longPress": false,
              "buttonId": 28,
              "maxActivationInterval": 0,
              "minActivationInterval": 50,
              "description": "Aileron trim axis / Aileron trim switch: right"
            }
          }
        ]
      },
      "description": "Trim"
    },
    {
      "uuid": "80e4ea4c-82a8-477e-89de-fd2fb37f4e8f",
      "axisToActionsMap": {
        "1": [
          {
            "type": "de.bwravencl.controllerbuddy.input.action.AxisToButtonAction",
            "data": {
              "longPress": false,
              "maxAxisValue": 1.0,
              "minAxisValue": 0.5,
              "buttonId": 34,
              "maxActivationInterval": 0,
              "minActivationInterval": 50,
              "description": "Engines turbosupercharger control"
            }
          },
          {
            "type": "de.bwravencl.controllerbuddy.input.action.AxisToButtonAction",
            "data": {
              "longPress": false,
              "maxAxisValue": -0.5,
              "minAxisValue": -1.0,
              "buttonId": 33,
              "maxActivationInterval": 0,
              "minActivationInterval": 50,
              "description": "Engines turbosupercharger control"
            }
          }
        ]
      },
      "buttonToActionsMap": {
        "4": [
          {
            "type": "de.bwravencl.controllerbuddy.input.action.ButtonToButtonAction",
            "data": {
              "longPress": false,
              "buttonId": 6,
              "maxActivationInterval": 0,
              "minActivationInterval": 50,
              "description": "Switch water radiators control mode: manual/auto"
            }
          }
        ],
        "11": [
          {
            "type": "de.bwravencl.controllerbuddy.input.action.ButtonToButtonAction",
            "data": {
              "longPress": false,
              "buttonId": 10,
              "maxActivationInterval": 0,
              "minActivationInterval": 50,
              "description": "Water radiators shutters control axis / Bf-109/110 and British aircraft water radiator: close"
            }
          }
        ],
        "12": [
          {
            "type": "de.bwravencl.controllerbuddy.input.action.ButtonToButtonAction",
            "data": {
              "longPress": false,
              "buttonId": 11,
              "maxActivationInterval": 0,
              "minActivationInterval": 50,
              "description": "Water radiators shutters control axis / Bf-109/110 and British aircraft water radiator: open"
            }
          }
        ],
        "13": [
          {
            "type": "de.bwravencl.controllerbuddy.input.action.ButtonToButtonAction",
            "data": {
              "longPress": false,
              "buttonId": 12,
              "maxActivationInterval": 0,
              "minActivationInterval": 50,
              "description": "He-111, Bf-110 oil radiators: close one step"
            }
          }
        ],
        "14": [
          {
            "type": "de.bwravencl.controllerbuddy.input.action.ButtonToButtonAction",
            "data": {
              "longPress": false,
              "buttonId": 13,
              "maxActivationInterval": 0,
              "minActivationInterval": 50,
              "description": "He-111, Bf-110 oil radiators: open one step"
            }
          }
        ]
      },
      "description": "Turbo / Cowl"
    },
    {
      "uuid": "bdcdac57-9f20-4e59-ad7b-47f7bc65f92a",
      "axisToActionsMap": {},
      "buttonToActionsMap": {
        "4": [
          {
            "type": "de.bwravencl.controllerbuddy.input.action.ButtonToButtonAction",
            "data": {
              "longPress": false,
              "buttonId": 3,
              "maxActivationInterval": 0,
              "minActivationInterval": 50,
              "description": "Eject"
            }
          }
        ],
        "11": [
          {
            "type": "de.bwravencl.controllerbuddy.input.action.ButtonToKeyAction",
            "data": {
              "activation": "REPEAT",
              "keystroke": {
                "keyCodes": [
                  "F1"
                ],
                "modifierCodes": []
              },
              "longPress": false,
              "maxActivationInterval": 0,
              "minActivationInterval": 50,
              "description": "Camera: player cockpit"
            }
          }
        ],
        "12": [
          {
            "type": "de.bwravencl.controllerbuddy.input.action.ButtonToKeyAction",
            "data": {
              "activation": "REPEAT",
              "keystroke": {
                "keyCodes": [
                  "O"
                ],
                "modifierCodes": []
              },
              "longPress": false,
              "maxActivationInterval": 0,
              "minActivationInterval": 50,
              "description": "Show/hide mission briefing"
            }
          }
        ],
        "13": [
          {
            "type": "de.bwravencl.controllerbuddy.input.action.ButtonToKeyAction",
            "data": {
              "activation": "REPEAT",
              "keystroke": {
                "keyCodes": [
                  "F2"
                ],
                "modifierCodes": []
              },
              "longPress": false,
              "maxActivationInterval": 0,
              "minActivationInterval": 50,
              "description": "External free camera at player plane"
            }
          }
        ],
        "14": [
          {
            "type": "de.bwravencl.controllerbuddy.input.action.ButtonToButtonAction",
            "data": {
              "longPress": false,
              "buttonId": 32,
              "maxActivationInterval": 0,
              "minActivationInterval": 50,
              "description": "Switch to a next free combat post"
            }
          }
        ]
      },
      "description": "View / Eject"
    }
  ],
  "showOverlay": true,
  "version": "1.4",
  "virtualAxisToOverlayAxisMap": {
    "S1": {
      "color": -65536,
      "inverted": false
    },
    "S0": {
      "color": -16776961,
      "inverted": false
    },
    "Z": {
      "color": -16777216,
      "inverted": false
    }
  }
}